xrd_learn/__init__.py
xrd_learn/rsm_viz.py
xrd_learn/skeleton.py
xrd_learn/xrd_utils.py
xrd_learn/xrd_viz.py
XRD_Learn-1.2.0.dist-info/LICENSE.txt
XRD_Learn-1.2.0.dist-info/METADATA
XRD_Learn-1.2.0.dist-info/WHEEL
XRD_Learn-1.2.0.dist-info/top_level.txt
XRD_Learn-1.2.0.dist-info/RECORD
