Metadata-Version: 2.2
Name: XRD-Learn
Version: 1.2.0
Summary: A Python package for visualizing and analyzing X-ray Diffraction (XRD) experimental data, providing tools to process, visualize, and extract meaningful insights from XRD patterns and measurements.
Home-page: https://github.com/pyscaffold/pyscaffold/
Author: Joshua C. Agar
Author-email: jca92@drexel.edu
Maintainer: Joshua C. Agar, Yichen Guo
Maintainer-email: jca92@drexel.edu, yig319@lehigh.edu
License: MIT
Project-URL: Documentation, https://pyscaffold.org/
Platform: any
Classifier: Development Status :: 4 - Beta
Classifier: Programming Language :: Python
License-File: LICENSE.txt
Requires-Dist: importlib-metadata; python_version < "3.8"
Provides-Extra: testing
Requires-Dist: setuptools; extra == "testing"
Requires-Dist: pytest; extra == "testing"
Requires-Dist: pytest-cov; extra == "testing"
